hello_simple_emoji_world/__init__.py
hello_simple_emoji_world-0.1.0.dist-info/LICENSE
hello_simple_emoji_world-0.1.0.dist-info/WHEEL
hello_simple_emoji_world-0.1.0.dist-info/METADATA
hello_simple_emoji_world-0.1.0.dist-info/RECORD
